{
	"name": "dataflow1",
	"properties": {
		"type": "MappingDataFlow",
		"typeProperties": {
			"sources": [
				{
					"dataset": {
						"referenceName": "AzureSql",
						"type": "DatasetReference"
					},
					"name": "source1"
				}
			],
			"sinks": [
				{
					"dataset": {
						"referenceName": "CosmosDbContainer002",
						"type": "DatasetReference"
					},
					"name": "sink1"
				}
			],
			"transformations": [],
			"scriptLines": [
				"source(allowSchemaDrift: true,",
				"     validateSchema: false,",
				"     isolationLevel: 'READ_UNCOMMITTED',",
				"     query: 'SELECT [value] FROM OPENJSON(\\n  (SELECT\\n    modelname=\\'Cantiere\\',\\n    o.idAppalto,\\n    o.[Data] as DataCantiere,\\n    o.Descrizione,\\n    o.Pioggia,\\n    o.OreAutocarro,\\n    o.UserId,\\n    (select IdOre, IdPersona, Ore from CantiereOre od where od.IdCantiere = o.IdCantiere for json auto) as OreUomo\\n   FROM Cantiere o FOR JSON PATH)\\n)',",
				"     format: 'query') ~> source1",
				"source1 sink(allowSchemaDrift: true,",
				"     validateSchema: false,",
				"     deletable:false,",
				"     insertable:true,",
				"     updateable:false,",
				"     upsertable:false,",
				"     format: 'document',",
				"     skipDuplicateMapInputs: true,",
				"     skipDuplicateMapOutputs: true) ~> sink1"
			]
		}
	}
}